{
    "key": "group_5dd980788f4c4",
    "title": "Site Options",
    "fields": [
        {
            "key": "field_5dd980862feb3",
            "label": "Google Maps API Key",
            "name": "google_maps_api_key",
            "type": "text",
            "instructions": "API key used to load Google Maps API in ACF groups.",
            "required": 0,
            "conditional_logic": 0,
            "wrapper": {
                "width": "",
                "class": "",
                "id": ""
            },
            "default_value": "",
            "placeholder": "",
            "prepend": "",
            "append": "",
            "maxlength": ""
        }
    ],
    "location": [
        [
            {
                "param": "options_page",
                "operator": "==",
                "value": "acf-options-theme-options"
            }
        ]
    ],
    "menu_order": 0,
    "position": "normal",
    "style": "default",
    "label_placement": "top",
    "instruction_placement": "label",
    "hide_on_screen": "",
    "active": 1,
    "description": "",
    "modified": 1585273182
}